awsovpn/__init__.py
awsovpn/__main__.py
awsovpn-0.5.dist-info/LICENSE
awsovpn-0.5.dist-info/METADATA
awsovpn-0.5.dist-info/WHEEL
awsovpn-0.5.dist-info/entry_points.txt
awsovpn-0.5.dist-info/top_level.txt
awsovpn-0.5.dist-info/RECORD
