Metadata-Version: 2.1
Name: awsovpn
Version: 0.5
Summary: Simple script for easy creation of OpenVPN instance on AWS
Home-page: https://awsovpn.readthedocs.io/
Author: Flying Hippo
Author-email: admin@flyinghippo.com
Project-URL: Source, https://github.com/parleer/awsovpn/
Project-URL: Documentation, https://awsovpn.readthedocs.io/en/latest/
Project-URL: Packaging tutorial, https://packaging.python.org/tutorials/packaging-projects/
Classifier: Intended Audience :: Developers
Classifier: License :: OSI Approved :: Apache Software License
Classifier: Natural Language :: English
Classifier: Operating System :: MacOS :: MacOS X
Classifier: Operating System :: POSIX
Classifier: Operating System :: POSIX :: BSD
Classifier: Operating System :: POSIX :: Linux
Classifier: Operating System :: Microsoft :: Windows
Classifier: Programming Language :: Python
Classifier: Programming Language :: Python :: 3
Classifier: Programming Language :: Python :: 3 :: Only
Classifier: Programming Language :: Python :: 3.8
Classifier: Programming Language :: Python :: 3.9
Classifier: Programming Language :: Python :: 3.10
Classifier: Programming Language :: Python :: 3.11
Classifier: Programming Language :: Python :: 3.12
Classifier: Programming Language :: Python :: Implementation :: CPython
Requires-Python: >=3.8
License-File: LICENSE
Requires-Dist: pkginfo >=1.8.1
Requires-Dist: boto3 ~=1.34.11
Requires-Dist: paramiko ~=3.4.0
Requires-Dist: importlib-metadata >=3.6
Requires-Dist: python-dotenv ==1.0.0
